{
	"id": "ce2d583a-29a0-4a7e-a315-eaf96d134c53",
	"name": "Agora-Development",
	"values": [
		{
			"key": "APPID",
			"value": "66a3bea50e5d498d860667718de624d5",
			"enabled": true
		},
		{
			"key": "CustomerID",
			"value": "4e269955bbb942b5a4d819b6d9820e30",
			"enabled": true
		},
		{
			"key": "CustomerCertificate",
			"value": "50071a3ea6ed46078f1c170da7116eba",
			"enabled": true
		},
		{
			"key": "token",
			"value": "",
			"enabled": true
		},
		{
			"key": "resourceId",
			"value": "",
			"enabled": true
		},
		{
			"key": "AccessChannel",
			"value": "pLaHyFscIlHZRU2jcS2B",
			"enabled": true
		},
		{
			"key": "RecordingUID",
			"value": "00000000000000000000000000000000",
			"enabled": true
		},
		{
			"key": "Vendor",
			"value": 1,
			"enabled": true
		},
		{
			"key": "Region",
			"value": 4,
			"enabled": true
		},
		{
			"key": "Bucket",
			"value": "",
			"enabled": true
		},
		{
			"key": "AccessKey",
			"value": "",
			"enabled": true
		},
		{
			"key": "SecretKey",
			"value": "",
			"enabled": true
		},
		{
			"key": "sid",
			"value": "",
			"enabled": true
		}
	],
	"_postman_variable_scope": "environment",
	"_postman_exported_at": "2020-05-06T02:16:21.591Z",
	"_postman_exported_using": "Postman/7.23.0"
}